README.md
setup.py
tus.py
tus.py.egg-info/PKG-INFO
tus.py.egg-info/SOURCES.txt
tus.py.egg-info/dependency_links.txt
tus.py.egg-info/entry_points.txt
tus.py.egg-info/requires.txt
tus.py.egg-info/top_level.txt
tus.py.egg-info/zip-safe